num2kor/__init__.py
num2kor/num2kor.py
Num2Kor-1.0.3.dist-info/METADATA
Num2Kor-1.0.3.dist-info/WHEEL
Num2Kor-1.0.3.dist-info/top_level.txt
Num2Kor-1.0.3.dist-info/RECORD
